imax/__init__.py
imax/color_transforms.py
imax/project.py
imax/randaugment.py
imax/transforms.py
imax-0.0.1b11.dist-info/LICENSE
imax-0.0.1b11.dist-info/METADATA
imax-0.0.1b11.dist-info/WHEEL
imax-0.0.1b11.dist-info/top_level.txt
imax-0.0.1b11.dist-info/RECORD
