Metadata-Version: 2.1
Name: imax
Version: 0.0.1b11
Summary: Image augmentation library for Jax
Home-page: https://github.com/4rtemi5/imax
Author: Raphael Pisoni
Author-email: raphael.pisoni@gmail.com
Classifier: Programming Language :: Python :: 3
Classifier: License :: OSI Approved :: Apache Software License
Classifier: Operating System :: OS Independent
Requires-Python: >=3.8
License-File: LICENSE
Requires-Dist: jax
Requires-Dist: jaxlib
